{"results": [{"name": "Kallang Sports Centre", "lat": 1.30529630300381, "long": 103.879604576327}, {"name": "Katong Swimming Complex", "lat": 1.30210564041254, "long": 103.886081886713}, {"name": "Pasir Ris Sports Centre", "lat": 1.37444845586245, "long": 103.95182250042}, {"name": "Queenstown Sports Centre", "lat": 1.29672720043947, "long": 103.802435215916}, {"name": "Sengkang Sports Centre", "lat": 1.39549658393931, "long": 103.885789255152}, {"name": "Serangoon Sports Centre", "lat": 1.35594654934782, "long": 103.874383973531}, {"name": "St Wilfrid Sports Complex", "lat": 1.32522689348828, "long": 103.861719012118}, {"name": "Tampines Swimming Complex", "lat": 1.35429510351818, "long": 103.93963580414}, {"name": "Toa Payoh Sports Centre", "lat": 1.33028646889072, "long": 103.851566352891}, {"name": "Woodlands Sports Centre", "lat": 1.43489537703518, "long": 103.780306573729}, {"name": "Yio Chu Kang Sports Centre", "lat": 1.3834708234938, "long": 103.845866608165}, {"name": "Yishun Sports Centre", "lat": 1.41201836574556, "long": 103.83117739651}, {"name": "Yishun Swimming Complex", "lat": 1.42406332292719, "long": 103.833692367151}, {"name": "Ang Mo Kio Swimming Complex", "lat": 1.36307894845156, "long": 103.849851705062}, {"name": "Bedok Sports Centre", "lat": 1.32638079784507, "long": 103.936716000861}, {"name": "Bishan Sports Centre", "lat": 1.35528262760188, "long": 103.850922071159}, {"name": "Bukit Batok Swimming Complex", "lat": 1.34433159736434, "long": 103.747954226702}, {"name": "Bukit Gombak Sports Centre", "lat": 1.35979953687728, "long": 103.75217022107}, {"name": "Burghley Squash and Tennis Centre", "lat": 1.35939081783085, "long": 103.860486528063}, {"name": "Choa Chu Kang Sports Centre", "lat": 1.39066617204386, "long": 103.747920712445}, {"name": "Clementi Sports Centre", "lat": 1.31101498462879, "long": 103.764861415667}, {"name": "Clementi Stadium", "lat": 1.30976459874851, "long": 103.762488569953}, {"name": "Delta Sports Centre", "lat": 1.2893742892013, "long": 103.820016552841}, {"name": "Farrer Park Field", "lat": 1.31171149348533, "long": 103.849500514144}, {"name": "Farrer Park Tennis Centre", "lat": 1.31171149348533, "long": 103.849500514144}, {"name": "Geylang East Swimming Complex", "lat": 1.32095367310021, "long": 103.887659823397}, {"name": "Geylang Field", "lat": 1.30983699500093, "long": 103.877503154652}, {"name": "Hougang Sports Centre", "lat": 1.37057348785749, "long": 103.88807173322}, {"name": "Jalan Besar Sports Centre", "lat": 1.31085491048578, "long": 103.859961717518}, {"name": "Jurong East Sports Centre", "lat": 1.34685582634484, "long": 103.729175057307}, {"name": "Jurong West Sports Centre", "lat": 1.33841806492775, "long": 103.69376890219}, {"name": "Kallang Basin Swimming Complex", "lat": 1.32255951909401, "long": 103.872491018144}]}